README.rst
setup.py
zmq_legos/__init__.py
zmq_legos.egg-info/PKG-INFO
zmq_legos.egg-info/SOURCES.txt
zmq_legos.egg-info/dependency_links.txt
zmq_legos.egg-info/requires.txt
zmq_legos.egg-info/top_level.txt
zmq_legos/mdp/__init__.py
zmq_legos/mdp/__main__.py
zmq_legos/mdp/client.py
zmq_legos/mdp/scheduler.py
zmq_legos/mdp/worker.py