Metadata-Version: 1.1
Name: zmq-legos
Version: 0.1.3
Summary: Building Blocks (Legos) using ZeroMQ for applications
Home-page: https://gitlab.aves.io/costrouc/zmq_legos
Author: Christopher Ostrouchov
Author-email: chris.ostrouchov+zmq_legos@gmail.com
License: UNKNOWN
Download-URL: https://gitlab.aves.io/costrouc/pysrim/repository/archive.zip?ref=v0.1.3
Keywords: zeromq python mpd
Platform: UNKNOWN
Classifier: Programming Language :: Python :: 3.5
Classifier: Programming Language :: Python :: 3.6
